django_startsubapp-1.0.0.dist-info/licenses/LICENSE
startsubapp/__init__.py
startsubapp/apps.py
startsubapp/management/commands/startsubapp.py
django_startsubapp-1.0.0.dist-info/METADATA
django_startsubapp-1.0.0.dist-info/WHEEL
django_startsubapp-1.0.0.dist-info/top_level.txt
django_startsubapp-1.0.0.dist-info/RECORD
