Metadata-Version: 2.4
Name: django-startsubapp
Version: 1.0.0
Summary: A Django management command to create apps in a subdirectory (e.g., apps/) for better project organization
Home-page: https://github.com/Saman-naruee/django-startsubapp
Author: Saman Naruee
Author-email: Saman Naruee <samannaruee@gmail.com>
License: MIT
Project-URL: Homepage, https://github.com/Saman-naruee/django-startsubapp
Project-URL: Documentation, https://github.com/Saman-naruee/django-startsubapp#readme
Project-URL: Repository, https://github.com/Saman-naruee/django-startsubapp.git
Project-URL: Issues, https://github.com/Saman-naruee/django-startsubapp/issues
Keywords: django,management-command,app-structure,django-apps
Classifier: Environment :: Web Environment
Classifier: Framework :: Django
Classifier: Framework :: Django :: 3.2
Classifier: Framework :: Django :: 4.0
Classifier: Framework :: Django :: 4.1
Classifier: Framework :: Django :: 4.2
Classifier: Framework :: Django :: 5.0
Classifier: Intended Audience :: Developers
Classifier: License :: OSI Approved :: MIT License
Classifier: Operating System :: OS Independent
Classifier: Programming Language :: Python
Classifier: Programming Language :: Python :: 3
Classifier: Programming Language :: Python :: 3.8
Classifier: Programming Language :: Python :: 3.9
Classifier: Programming Language :: Python :: 3.10
Classifier: Programming Language :: Python :: 3.11
Classifier: Programming Language :: Python :: 3.12
Classifier: Topic :: Software Development :: Libraries :: Python Modules
Classifier: Topic :: Software Development :: Libraries :: Application Frameworks
Requires-Python: >=3.8
License-File: LICENSE
Requires-Dist: Django>=3.2
Provides-Extra: dev
Requires-Dist: pytest>=7.0; extra == "dev"
Requires-Dist: pytest-django>=4.5; extra == "dev"
Requires-Dist: black>=22.0; extra == "dev"
Requires-Dist: isort>=5.0; extra == "dev"
Requires-Dist: flake8>=4.0; extra == "dev"
Dynamic: license-file
